pampy/__init__.py
pampy/helpers.py
pampy/pampy.py
tests/__init__.py
tests/test_basic.py
tests/test_dataclass.py
tests/test_dict.py
tests/test_elaborate.py
tests/test_iterable.py
pampy-0.2.1.dist-info/LICENSE
pampy-0.2.1.dist-info/METADATA
pampy-0.2.1.dist-info/WHEEL
pampy-0.2.1.dist-info/top_level.txt
pampy-0.2.1.dist-info/RECORD
