Metadata-Version: 2.1
Name: pampy
Version: 0.2.1
Summary: The Pattern Matching for Python you always dreamed of
Home-page: https://github.com/santinic/pampy
Author: Claudio Santini
Author-email: hireclaudio@gmail.com
License: UNKNOWN
Platform: any
Classifier: Programming Language :: Python :: 3
Classifier: License :: OSI Approved :: MIT License
Classifier: Operating System :: OS Independent
Requires-Python: >3.6
